tbl/__init__.py
tbl/bots.py
toxicbl/__init__.py
toxicbl/bots.py
toxicbl/data.py
toxicbl/users.py
toxicbl-2.3.1.dist-info/METADATA
toxicbl-2.3.1.dist-info/WHEEL
toxicbl-2.3.1.dist-info/top_level.txt
toxicbl-2.3.1.dist-info/RECORD
