Metadata-Version: 2.1
Name: toxicbl
Version: 2.3.1
Summary: The official API package for Toxic's bot list using Python 3
Home-page: https://github.com/kokkoooo/tbl.py
Author: Jake
Author-email: jakediserin@gmail.com
License: MIT
Platform: UNKNOWN
Classifier: Programming Language :: Python :: 3
Classifier: License :: OSI Approved :: MIT License
Classifier: Operating System :: OS Independent
Requires-Python: >=3.6
Requires-Dist: requests
